Metadata-Version: 2.4
Name: agenspy
Version: 0.0.1
Summary: Agenspy (Agentic-DSPy)- Protocol-first AI agent framework built on DSPy - supporting MCP, Agent2Agent, and future protocols
Home-page: https://github.com/superagenticai/agenspy
Author: Shashi Jagtap
Author-email: Shashi Jagtap <shashi@super-agentic.ai>
License: MIT License
Project-URL: homepage, https://github.com/superagenticai/agenspy
Project-URL: repository, https://github.com/superagenticai/agenspy
Project-URL: documentation, https://agenspy.readthedocs.io
Classifier: Development Status :: 3 - Alpha
Classifier: Intended Audience :: Developers
Classifier: License :: OSI Approved :: MIT License
Classifier: Programming Language :: Python :: 3
Classifier: Programming Language :: Python :: 3.9
Classifier: Programming Language :: Python :: 3.10
Classifier: Programming Language :: Python :: 3.11
Classifier: Topic :: Scientific/Engineering :: Artificial Intelligence
Classifier: Topic :: Software Development :: Libraries :: Python Modules
Requires-Python: >=3.9
License-File: LICENSE
Requires-Dist: dspy
Requires-Dist: asyncio
Requires-Dist: typing-extensions
Requires-Dist: pydantic>=2.0
Requires-Dist: fastapi>=0.100.0
Requires-Dist: uvicorn>=0.20.0
Requires-Dist: click>=8.0
Requires-Dist: pyyaml>=6.0
Provides-Extra: mcp
Requires-Dist: mcp>=1.0.0; extra == "mcp"
Provides-Extra: dev
Requires-Dist: pytest>=6.2.5; extra == "dev"
Requires-Dist: black; extra == "dev"
Requires-Dist: ruff; extra == "dev"
Requires-Dist: mypy; extra == "dev"
Requires-Dist: pre-commit>=3.0.0; extra == "dev"
Provides-Extra: examples
Requires-Dist: openai>=1.0.0; extra == "examples"
Requires-Dist: requests>=2.31.0; extra == "examples"
Provides-Extra: servers
Requires-Dist: fastapi>=0.100.0; extra == "servers"
Requires-Dist: uvicorn>=0.20.0; extra == "servers"
Dynamic: author
Dynamic: home-page
Dynamic: license-file
Dynamic: requires-python
